pygdrive3/__init__.py
pygdrive3/service.py
pygdrive3fixed/__init__.py
pygdrive3fixed/service.py
test/__init__.py
test/context.py
test/list.py
test/test.py
pygdrive3fixed-0.6.8.dist-info/LICENSE.md
pygdrive3fixed-0.6.8.dist-info/METADATA
pygdrive3fixed-0.6.8.dist-info/WHEEL
pygdrive3fixed-0.6.8.dist-info/top_level.txt
pygdrive3fixed-0.6.8.dist-info/RECORD
