Metadata-Version: 2.1
Name: pygdrive3fixed
Version: 0.6.8
Summary: Use Google Drive API v3 with a python interface
Home-page: https://github.com/TA40/pygdrive3
Author: Matheus Almeida / Tami
Author-email: mat.almeida@live.com
License: MIT
Platform: UNKNOWN
Classifier: Programming Language :: Python :: 3
Classifier: License :: OSI Approved :: MIT License
Classifier: Operating System :: OS Independent
Requires-Dist: apiclient
Requires-Dist: httplib2
Requires-Dist: oauth2client
